<?xml version="1.0" encoding="utf-8" ?><dwsync><file name="linndustries_logo.png.png" server="linnard.com/new/" local="3451862201" remote="16336796688" /><file name="goAway.jpg" server="linnard.com/new/" local="3452125065" remote="16337059308" /><file name="linndustries-logo.png" server="linnard.com/new/" local="3451894620" remote="16336796508" /><file name="linndustries_logo.png" server="linnard.com/new/" local="3451894680" remote="16336796568" /><file name="teddy02.gif" server="linnard.com/new/" local="3452140920" remote="16337042808" /><file name="teddy1.jpg" server="linnard.com/new/" local="3452141160" remote="16337043048" /><file name="teddy1.png" server="linnard.com/new/" local="3452141040" remote="16337042928" /><file name="teddy10.gif" server="linnard.com/new/" local="3452140920" remote="16337042808" /><file name="teddy13.gif" server="linnard.com/new/" local="3452140920" remote="16337042808" /><file name="teddy2.jpg" server="linnard.com/new/" local="3452141280" remote="16337043168" /><file name="teddy3.jpg" server="linnard.com/new/" local="3452141280" remote="16337043168" /><file name="mac_ewan1.jpg" server="linnard.com/new/" local="3453167028" remote="16338101268" /><file name="MacE_4225.jpg" server="linnard.com/new/" local="3453416036" remote="16338354228" /><file name="MacE4226.jpg" server="linnard.com/new/" local="3453416921" remote="16338354228" /><file name="macE4227.jpg" server="linnard.com/new/" local="3453417292" remote="16338354228" /><file name="macE4233.jpg" server="linnard.com/new/" local="3453417599" remote="16338354228" /><file name="macE4236.jpg" server="linnard.com/new/" local="3453418350" remote="16338354228" /><file name="macE4237.jpg" server="linnard.com/new/" local="3453418644" remote="16338354228" /><file name="macE4240.jpg" server="linnard.com/new/" local="3453420687" remote="16338355008" /><file name="macE4242.jpg" server="linnard.com/new/" local="3453418851" remote="16338354228" /><file name="macE4243.jpg" server="linnard.com/new/" local="3453418982" remote="16338354228" /><file name="macE4245.jpg" server="linnard.com/new/" local="3453419762" remote="16338354228" /><file name="macE4264.jpg" server="linnard.com/new/" local="3453942725" remote="16338877128" /><file name="macE4265.jpg" server="linnard.com/new/" local="3453941419" remote="16338877128" /><file name="macE4267.jpg" server="linnard.com/new/" local="3453941324" remote="16338877128" /><file name="macE4268.jpg" server="linnard.com/new/" local="3453941262" remote="16338877128" /><file name="macE4269.jpg" server="linnard.com/new/" local="3453941169" remote="16338877128" /><file name="macE4271.jpg" server="linnard.com/new/" local="3453941048" remote="16338877188" /><file name="macE4272.jpg" server="linnard.com/new/" local="3453940936" remote="16338877188" /><file name="david4.jpg" server="linnard.com/new/" local="3454200246" remote="16339134588" /><file name="david3.jpg" server="linnard.com/new/" local="3454200371" remote="16339134648" /><file name="david400.jpg" server="linnard.com/new/" local="3454200440" remote="16339134708" /><file name="david450.jpg" server="linnard.com/new/" local="3454201967" remote="16339136268" /><file name="david3.psd" server="linnard.com/new/" local="662301827561353333" remote="-1" /><file name="down_arrow.png" server="linnard.com/new/" local="3455163780" remote="16340065668" /><file name="down_arrow2.png" server="linnard.com/new/" local="3455232480" remote="16340134368" /><file name="down_arrows.png" server="linnard.com/new/" local="3455161800" remote="16340063688" /><file name="icon_search.gif" server="linnard.com/new/" local="3455233440" remote="16340135328" /><file name="icon_search.png" server="linnard.com/new/" local="3455233500" remote="16340135388" /><file name="right_arrow.png" server="linnard.com/new/" local="3455163780" remote="16340065668" /><file name="twill.jpg" server="linnard.com/new/" local="3455673961" remote="16340608248" /><file name="twill2.jpg" server="linnard.com/new/" local="3455667237" remote="16340601588" /><file name="splotch_320.jpg" server="linnard.com/new/" local="3455663781" remote="16340603748" /><file name="splotch_319.jpg" server="linnard.com/new/" local="3455663737" remote="16340603748" /><file name="splotch_318.jpg" server="linnard.com/new/" local="3455663684" remote="16340603748" /><file name="splotch_317.jpg" server="linnard.com/new/" local="3455663632" remote="16340603748" /><file name="splotch_316.jpg" server="linnard.com/new/" local="3455663324" remote="16340603748" /><file name="splotch_315.jpg" server="linnard.com/new/" local="3455663250" remote="16340603748" /><file name="splotch_313.jpg" server="linnard.com/new/" local="3455663093" remote="16340603748" /><file name="zero_stock.jpg" server="linnard.com/new/" local="3455946780" remote="16340848668" /><file name="zero_stock2.jpg" server="linnard.com/new/" local="3455946840" remote="16340848728" /><file name="ransom359.jpg" server="linnard.com/new/" local="3456438884" remote="16341373488" /><file name="ransom360.jpg" server="linnard.com/new/" local="3456438777" remote="16341373488" /><file name="ransom361.jpg" server="linnard.com/new/" local="3456438628" remote="16341373488" /><file name="ransom362.jpg" server="linnard.com/new/" local="3456438566" remote="16341373488" /><file name="ransom365.jpg" server="linnard.com/new/" local="3456438418" remote="16341373488" /><file name="ransom371.jpg" server="linnard.com/new/" local="3456438249" remote="16341373488" /><file name="ransom373.jpg" server="linnard.com/new/" local="3456438131" remote="16341373488" /><file name="ransom375.jpg" server="linnard.com/new/" local="3456447748" remote="16341382068" /><file name="ransom377.jpg" server="linnard.com/new/" local="3456437804" remote="16341373488" /><file name="ransom376.jpg" server="linnard.com/new/" local="3456447943" remote="16341382248" /><file name="ModernContainer.jpg" server="linnard.com/new/" local="3459812280" remote="16344714168" /><file name="ModernContainer_200.jpg" server="linnard.com/new/" local="3459812280" remote="16344714168" /><file name="ModernContainer_250.jpg" server="linnard.com/new/" local="3459812280" remote="16344714168" /><file name="ModernContainer_large.JPG" server="linnard.com/new/" local="3459812400" remote="16344714288" /><file name="radio_62.jpg" server="linnard.com/new/" local="3460680379" remote="16345615368" /><file name="radio_61.jpg" server="linnard.com/new/" local="3460679622" remote="16345615368" /><file name="radio_60.jpg" server="linnard.com/new/" local="3460681057" remote="16345615368" /><file name="radio_58.jpg" server="linnard.com/new/" local="3460679574" remote="16345615368" /><file name="radio_51.jpg" server="linnard.com/new/" local="3460679527" remote="16345615368" /><file name="radio_50.jpg" server="linnard.com/new/" local="3460679504" remote="16345615368" /><file name="radio_49.jpg" server="linnard.com/new/" local="3460679477" remote="16345615368" /><file name="radio_61.gif" server="linnard.com/new/" local="3460680530" remote="16345615368" /><file name="prop1.jpg" server="linnard.com//new/" local="3473022672" remote="16357956948" /><file name="yellow1.jpg" server="linnard.com//new/" local="3473022249" remote="16357956528" /><file name="cross_hairs.jpg" server="linnard.com//new/" local="3473022381" remote="16357956648" /><file name="concord.jpg" server="linnard.com//new/" local="3473013860" remote="16357948128" /><file name="sub_set.jpg" server="linnard.com//new/" local="3473022485" remote="16357956768" /><file name="sub_bubbles.jpg" server="linnard.com//new/" local="3473022574" remote="16357956828" /><file name="speakers.jpg" server="linnard.com//new/" local="3473010331" remote="16357944588" /><file name="transistor2.jpg" server="linnard.com//new/" local="3473010549" remote="16357944828" /><file name="resistor2.jpg" server="linnard.com//new/" local="3473011166" remote="16357945428" /><file name="battery2.jpg" server="linnard.com//new/" local="3473010939" remote="16357945188" /><file name="david4.jpg" server="linnard.com//new/" local="3454232700" remote="16339134588" /><file name="david450.jpg" server="linnard.com//new/" local="3454234380" remote="16339136268" /><file name="linndustries_logo.png.png" server="linnard.com//new/" local="3451894800" remote="16336796688" /><file name="MacE4226.jpg" server="linnard.com//new/" local="3453452340" remote="16338354228" /><file name="macE4227.jpg" server="linnard.com//new/" local="3453452340" remote="16338354228" /><file name="macE4233.jpg" server="linnard.com//new/" local="3453452340" remote="16338354228" /><file name="macE4236.jpg" server="linnard.com//new/" local="3453452340" remote="16338354228" /><file name="macE4237.jpg" server="linnard.com//new/" local="3453452340" remote="16338354228" /><file name="macE4240.jpg" server="linnard.com//new/" local="3453453120" remote="16338355008" /><file name="macE4242.jpg" server="linnard.com//new/" local="3453452340" remote="16338354228" /><file name="macE4243.jpg" server="linnard.com//new/" local="3453452340" remote="16338354228" /><file name="macE4245.jpg" server="linnard.com//new/" local="3453452340" remote="16338354228" /><file name="macE4264.jpg" server="linnard.com//new/" local="3453975240" remote="16338877128" /><file name="macE4265.jpg" server="linnard.com//new/" local="3453975240" remote="16338877128" /><file name="macE4267.jpg" server="linnard.com//new/" local="3453975240" remote="16338877128" /><file name="macE4268.jpg" server="linnard.com//new/" local="3453975240" remote="16338877128" /><file name="macE4269.jpg" server="linnard.com//new/" local="3453975240" remote="16338877128" /><file name="macE4271.jpg" server="linnard.com//new/" local="3453975300" remote="16338877188" /><file name="macE4272.jpg" server="linnard.com//new/" local="3453975300" remote="16338877188" /><file name="MacE_4225.jpg" server="linnard.com//new/" local="3453452340" remote="16338354228" /><file name="radio_49.jpg" server="linnard.com//new/" local="3460713480" remote="16345615368" /><file name="radio_50.jpg" server="linnard.com//new/" local="3460713480" remote="16345615368" /><file name="radio_51.jpg" server="linnard.com//new/" local="3460713480" remote="16345615368" /><file name="radio_58.jpg" server="linnard.com//new/" local="3460713480" remote="16345615368" /><file name="radio_60.jpg" server="linnard.com//new/" local="3460713480" remote="16345615368" /><file name="radio_61.gif" server="linnard.com//new/" local="3460713480" remote="16345615368" /><file name="radio_61.jpg" server="linnard.com//new/" local="3460713480" remote="16345615368" /><file name="radio_62.jpg" server="linnard.com//new/" local="3460713480" remote="16345615368" /><file name="ransom359.jpg" server="linnard.com//new/" local="3472939863" remote="16357874508" /><file name="ransom360.jpg" server="linnard.com//new/" local="3456471600" remote="16357874508" /><file name="ransom361.jpg" server="linnard.com//new/" local="3472940398" remote="16357875048" /><file name="ransom362.jpg" server="linnard.com//new/" local="3456471600" remote="16357874508" /><file name="ransom365.jpg" server="linnard.com//new/" local="3472940018" remote="16357874508" /><file name="ransom371.jpg" server="linnard.com//new/" local="3472940050" remote="16357874508" /><file name="ransom373.jpg" server="linnard.com//new/" local="3472940108" remote="16357874508" /><file name="ransom375.jpg" server="linnard.com//new/" local="3456480180" remote="16357874508" /><file name="ransom376.jpg" server="linnard.com//new/" local="3456480360" remote="16357874508" /><file name="ransom377.jpg" server="linnard.com//new/" local="3456471600" remote="16357874508" /><file name="splotch_313.jpg" server="linnard.com//new/" local="3473025240" remote="16357959528" /><file name="splotch_315.jpg" server="linnard.com//new/" local="3473024028" remote="16357958328" /><file name="splotch_316.jpg" server="linnard.com//new/" local="3473026407" remote="16357960668" /><file name="splotch_317.jpg" server="linnard.com//new/" local="3473024786" remote="16357959048" /><file name="splotch_318.jpg" server="linnard.com//new/" local="3473024936" remote="16357959228" /><file name="splotch_319.jpg" server="linnard.com//new/" local="3455701860" remote="16340603748" /><file name="splotch_320.jpg" server="linnard.com//new/" local="3455701860" remote="16340603748" /><file name="sub_set2.jpg" server="linnard.com//new/" local="3462612180" remote="16347514068" /><file name="twill2.jpg" server="linnard.com//new/" local="3455699700" remote="16340601588" /><file name="jet_formation.png" server="linnard.com//new/" local="3463359456" remote="16348294068" /><file name="learJet.png" server="linnard.com//new/" local="3463360437" remote="16348294728" /><file name="blackbird.png" server="linnard.com//new/" local="3463361754" remote="16348296108" /><file name="jet_formation.jpg" server="linnard.com//new/" local="3463362114" remote="16348296528" /><file name="blackbird.jpg" server="linnard.com//new/" local="3473020802" remote="16357955088" /><file name="learJet.jpg" server="linnard.com//new/" local="3473020260" remote="16357954848" /><file name="f18.jpg" server="linnard.com//new/" local="3473020494" remote="16357954848" /><file name="david3.jpg" server="linnard.com//new/" local="2575432268682291763" remote="-4611743344196622152" /><file name="david3.psd" server="linnard.com//new/" local="2811996593444810869" remote="-1" /><file name="david400.jpg" server="linnard.com//new/" local="2575449860868336248" remote="-4611743344196622092" /><file name="goAway.jpg" server="linnard.com//new/" local="2561582820216749961" remote="-4611743344198697492" /><file name="mac_ewan1.jpg" server="linnard.com//new/" local="2576124961006757300" remote="-4611743344197655532" /><file name="twill.jpg" server="linnard.com//new/" local="2577321229660284521" remote="-4611743344195148552" /><file name="sub_set.psd" server="linnard.com//new/" local="3464070600" remote="16348972488" /><file name="sub_set2.psd" server="linnard.com//new/" local="3464070600" remote="16348972488" /><file name="pin.png" server="linnard.com//new/" local="3466269418" remote="16351200288" /><file name="pin.jpg" server="linnard.com//new/" local="3466269778" remote="16351200468" /><file name="mc1.jpg" server="linnard.com//new/" local="3469321889" remote="16354256388" /><file name="teddy1.jpg" server="linnard.com//new/" local="3469322943" remote="16354257228" /><file name="teddy3.jpg" server="linnard.com//new/" local="3469383966" remote="16354318248" /><file name="teddy2.jpg" server="linnard.com//new/" local="3469323236" remote="16354257528" /><file name="macE43.jpg" server="linnard.com//new/" local="3469384221" remote="16354318488" /><file name="macE45.jpg" server="linnard.com//new/" local="3469384376" remote="16354318668" /><file name="MacE68.jpg" server="linnard.com//new/" local="3469384631" remote="16354318908" /><file name="MacE72.jpg" server="linnard.com//new/" local="3469384740" remote="16354319028" /><file name="mc59.jpg" server="linnard.com//new/" local="3469398766" remote="16354333128" /><file name="mc73.jpg" server="linnard.com//new/" local="3469401300" remote="16354335648" /><file name="mc23.jpg" server="linnard.com//new/" local="3472865355" remote="16357799808" /><file name="mc26.jpg" server="linnard.com//new/" local="3472865604" remote="16357799868" /><file name="mc35.jpg" server="linnard.com//new/" local="3469405010" remote="16354339368" /><file name="splotch_13_470.jpg" server="linnard.com//new/" local="3469405577" remote="16354339908" /><file name="jet_formation_470.jpg" server="linnard.com//new/" local="3469407542" remote="16354341828" /><file name="yellow1_470.jpg" server="linnard.com//new/" local="3469407706" remote="16354342008" /><file name="ransom371_470.jpg" server="linnard.com//new/" local="3469408025" remote="16357874508" /><file name="speakers_470.jpg" server="linnard.com//new/" local="3469408218" remote="16354342488" /><file name="concord1_470.jpg" server="linnard.com//new/" local="3469408840" remote="16354343148" /><file name="pizza056.jpg" server="linnard.com//new/" local="3472871706" remote="16357805988" /><file name="pizza836.jpg" server="linnard.com//new/" local="3472937932" remote="16357872228" /><file name="pizza839.jpg" server="linnard.com//new/" local="3472935362" remote="16357869648" /><file name="pizza844.jpg" server="linnard.com//new/" local="3472936066" remote="16357870368" /><file name="pizza845.jpg" server="linnard.com//new/" local="3472937232" remote="16357871508" /><file name="mace_235.jpg" server="linnard.com//new/" local="3472952715" remote="16357887108" /><file name="mace_237.jpg" server="linnard.com//new/" local="3472953889" remote="16357888188" /><file name="mace_213.jpg" server="linnard.com//new/" local="3472951986" remote="16357888248" /><file name="mace_243.jpg" server="linnard.com//new/" local="3472954362" remote="16357888668" /><file name="mace_245.jpg" server="linnard.com//new/" local="3472954744" remote="16357889088" /><file name="mace_264.jpg" server="linnard.com//new/" local="3472955164" remote="16357889448" /><file name="mace_268.jpg" server="linnard.com//new/" local="3472955350" remote="16357889628" /><file name="mace_269.jpg" server="linnard.com//new/" local="3472959171" remote="16357893468" /><file name="mace_271.jpg" server="linnard.com//new/" local="3472959502" remote="16357893828" /><file name="radio_461.jpg" server="linnard.com//new/" local="3473012827" remote="16357947108" /><file name="bat242.jpg" server="linnard.com//new/" local="3473094908" remote="16358029428" /><file name="bat266.jpg" server="linnard.com//new/" local="3473091036" remote="16358026788" /><file name="bat3.jpg" server="linnard.com//new/" local="3473094070" remote="16358028348" /><file name="bat343.jpg" server="linnard.com//new/" local="3473093363" remote="16358027628" /><file name="bat1.jpg" server="linnard.com//new/" local="3473034820" remote="16358025768" /><file name="bat5.jpg" server="linnard.com//new/" local="3473095321" remote="16358029608" /><file name="fishy.jpg" server="linnard.com//" local="2793157561236256151" remote="3475987200" /><file name="x_15.jpg" server="linnard.com//" local="2124878791920698653" remote="3476160000" /><file name="bat1.jpg" server="linnard.com//" local="760774088963804740" remote="3473049600" /><file name="bat242.jpg" server="linnard.com//" local="760782885056887036" remote="3473049600" /><file name="bat266.jpg" server="linnard.com//" local="761029175661504988" remote="3473049600" /><file name="bat3.jpg" server="linnard.com//" local="761037971754530230" remote="3473049600" /><file name="bat343.jpg" server="linnard.com//" local="761046767847551731" remote="3473049600" /><file name="bat5.jpg" server="linnard.com//" local="760598167103421081" remote="3473049600" /><file name="battery2.jpg" server="linnard.com//" local="760606963196358907" remote="3472963200" /><file name="blackbird.jpg" server="linnard.com//" local="760615759289390978" remote="3473049600" /><file name="blackbird.png" server="linnard.com//" local="760624555372754138" remote="3469420800" /><file name="concord.jpg" server="linnard.com//" local="760633351475428452" remote="3472963200" /><file name="concord1_470.jpg" server="linnard.com//" local="760642147564845640" remote="3469420800" /><file name="cross_hairs.jpg" server="linnard.com//" local="760650943661481389" remote="3473049600" /><file name="david3.jpg" server="linnard.com//" local="760659739735681587" remote="3469420800" /><file name="david3.psd" server="linnard.com//" local="760668535828705397" remote="-1" /><file name="david4.jpg" server="linnard.com//" local="2078611342601971836" remote="3469420800" /><file name="david400.jpg" server="linnard.com//" local="2793172954377284216" remote="3469420800" /><file name="david450.jpg" server="linnard.com//" local="2779064021169696524" remote="3469420800" /><file name="down_arrow.png" server="linnard.com//" local="2082727914137296260" remote="3469420800" /><file name="down_arrow2.png" server="linnard.com//" local="3135371759267785184" remote="3469420800" /><file name="down_arrows.png" server="linnard.com//" local="3135380555360736712" remote="3469420800" /><file name="f18.jpg" server="linnard.com//" local="2793148765140293198" remote="3473049600" /><file name="goAway.jpg" server="linnard.com//" local="2807770070745563017" remote="3469420800" /><file name="icon_search.gif" server="linnard.com//" local="2084084711486041504" remote="3469420800" /><file name="icon_search.png" server="linnard.com//" local="3150965033172905436" remote="3469420800" /><file name="jet_formation.jpg" server="linnard.com//" local="3150973829274056258" remote="3469420800" /><file name="jet_formation.png" server="linnard.com//" local="2089311789772614624" remote="3469420800" /><file name="jet_formation_470.jpg" server="linnard.com//" local="2822321007644833078" remote="3469420800" /><file name="learJet.jpg" server="linnard.com//" local="2089320585875297636" remote="3473049600" /><file name="learJet.png" server="linnard.com//" local="760677331930886069" remote="3469420800" /><file name="linndustries-logo.png" server="linnard.com//" local="2782008513306540892" remote="3469420800" /><file name="linndustries_logo.png" server="linnard.com//" local="2782017309399563160" remote="3469420800" /><file name="linndustries_logo.png.png" server="linnard.com//" local="3142127158705503248" remote="3469420800" /><file name="mac_ewan1.jpg" server="linnard.com//" local="3142135954799797684" remote="3469420800" /><file name="MacE4226.jpg" server="linnard.com//" local="2798056985027117108" remote="3469420800" /><file name="macE4227.jpg" server="linnard.com//" local="2798065781120139316" remote="3469420800" /><file name="macE4233.jpg" server="linnard.com//" local="3149810545961959476" remote="3469420800" /><file name="macE4236.jpg" server="linnard.com//" local="3149819342054981684" remote="3469420800" /><file name="macE4237.jpg" server="linnard.com//" local="2777311399634239540" remote="3469420800" /><file name="macE4240.jpg" server="linnard.com//" local="2777320195727262528" remote="3469420800" /><file name="macE4242.jpg" server="linnard.com//" local="2777361977169117236" remote="3469420800" /><file name="macE4243.jpg" server="linnard.com//" local="2777370773262139444" remote="3469420800" /><file name="macE4245.jpg" server="linnard.com//" local="2784101983447384116" remote="3469420800" /><file name="macE4264.jpg" server="linnard.com//" local="2784110779540929224" remote="3469420800" /><file name="macE4265.jpg" server="linnard.com//" local="2785863401075604168" remote="3469420800" /><file name="macE4267.jpg" server="linnard.com//" local="2785872197168626376" remote="3469420800" /><file name="macE4268.jpg" server="linnard.com//" local="2083279868973251272" remote="3469420800" /><file name="macE4269.jpg" server="linnard.com//" local="2083288665066273480" remote="3469420800" /><file name="macE4271.jpg" server="linnard.com//" local="2784416443773451012" remote="3469420800" /><file name="macE4272.jpg" server="linnard.com//" local="2784425239866473220" remote="3469420800" /><file name="macE43.jpg" server="linnard.com//" local="2084095706616470045" remote="3469334400" /><file name="macE45.jpg" server="linnard.com//" local="2084104502709492408" remote="3469334400" /><file name="MacE68.jpg" server="linnard.com//" local="2789518177741740983" remote="3469334400" /><file name="MacE72.jpg" server="linnard.com//" local="2789526973834763300" remote="3469334400" /><file name="mace_213.jpg" server="linnard.com//" local="2787035480489790130" remote="3472963200" /><file name="mace_235.jpg" server="linnard.com//" local="2787044276582813067" remote="3472963200" /><file name="mace_237.jpg" server="linnard.com//" local="2807737085417558561" remote="3472963200" /><file name="mace_243.jpg" server="linnard.com//" local="2807745881510581242" remote="3472963200" /><file name="mace_245.jpg" server="linnard.com//" local="3138371227006080376" remote="3472963200" /><file name="mace_264.jpg" server="linnard.com//" local="3138380023099103004" remote="3472963200" /><file name="mace_268.jpg" server="linnard.com//" local="2791398342628808662" remote="3472963200" /><file name="mace_269.jpg" server="linnard.com//" local="2120467551266875075" remote="3472963200" /><file name="mace_271.jpg" server="linnard.com//" local="2819110433695279118" remote="3472963200" /><file name="MacE_4225.jpg" server="linnard.com//" local="2819119229768794164" remote="3469420800" /><file name="mc1.jpg" server="linnard.com//" local="2791415934811219617" remote="3469334400" /><file name="mc1.png" server="linnard.com//" local="2827026917411628300" remote="-1" /><file name="mc23.jpg" server="linnard.com//" local="2827035713508194379" remote="3472876800" /><file name="mc26.jpg" server="linnard.com//" local="2774978235979512132" remote="3472876800" /><file name="mc35.jpg" server="linnard.com//" local="2774987032069073746" remote="3469420800" /><file name="mc59.jpg" server="linnard.com//" local="2774995828162089710" remote="3469420800" /><file name="mc73.jpg" server="linnard.com//" local="2827044509597752532" remote="3469420800" /><file name="ModernContainer.jpg" server="linnard.com//" local="2827053305681185720" remote="3469420800" /><file name="ModernContainer_200.jpg" server="linnard.com//" local="2827062101774207928" remote="3469420800" /><file name="ModernContainer_250.jpg" server="linnard.com//" local="2827070897867230136" remote="3469420800" /><file name="ModernContainer_large.JPG" server="linnard.com//" local="2827079693960252464" remote="3469420800" /><file name="pin.jpg" server="linnard.com//" local="2827088490059732050" remote="3466220400" /><file name="pin.png" server="linnard.com//" local="2827211635362042602" remote="3466220400" /><file name="pizza056.jpg" server="linnard.com//" local="2827220431461667098" remote="3472876800" /><file name="pizza836.jpg" server="linnard.com//" local="2827229227554755532" remote="3472963200" /><file name="pizza839.jpg" server="linnard.com//" local="2827238023647775170" remote="3472963200" /><file name="pizza844.jpg" server="linnard.com//" local="2784480215466822786" remote="3472963200" /><file name="pizza845.jpg" server="linnard.com//" local="2784489011559846160" remote="3472963200" /><file name="prop1.jpg" server="linnard.com//" local="687067227484200656" remote="3473049600" /><file name="radio_461.jpg" server="linnard.com//" local="2827246819740874843" remote="3472963200" /><file name="radio_49.jpg" server="linnard.com//" local="2827255615821597704" remote="3469420800" /><file name="radio_50.jpg" server="linnard.com//" local="2827264411914619912" remote="3469420800" /><file name="radio_51.jpg" server="linnard.com//" local="2827273208007642120" remote="3469420800" /><file name="radio_58.jpg" server="linnard.com//" local="2827282004100664328" remote="3469420800" /><file name="radio_60.jpg" server="linnard.com//" local="2827290800193686536" remote="3469420800" /><file name="radio_61.gif" server="linnard.com//" local="2124935966509911048" remote="3469420800" /><file name="radio_61.jpg" server="linnard.com//" local="2124944762602933256" remote="3469420800" /><file name="radio_62.jpg" server="linnard.com//" local="2124953558695955464" remote="3469420800" /><file name="ransom359.jpg" server="linnard.com//" local="2124962354801204055" remote="3472963200" /><file name="ransom360.jpg" server="linnard.com//" local="2124971150877758000" remote="3472963200" /><file name="ransom361.jpg" server="linnard.com//" local="2124979946987249006" remote="3472963200" /><file name="ransom362.jpg" server="linnard.com//" local="2124988743063802416" remote="3472963200" /><file name="ransom365.jpg" server="linnard.com//" local="2825373251927071730" remote="3472963200" /><file name="ransom371.jpg" server="linnard.com//" local="2825382048020093970" remote="3472963200" /><file name="ransom371_470.jpg" server="linnard.com//" local="2825390844109584153" remote="3472963200" /><file name="ransom373.jpg" server="linnard.com//" local="2825399640206138444" remote="3472963200" /><file name="ransom375.jpg" server="linnard.com//" local="2825408436282700724" remote="3472963200" /><file name="ransom376.jpg" server="linnard.com//" local="2825417232375723112" remote="3472963200" /><file name="ransom377.jpg" server="linnard.com//" local="2825426028468736560" remote="3472963200" /><file name="ranson376.jpg" server="linnard.com//" local="2825434824578227371" remote="-1" /><file name="resistor2.jpg" server="linnard.com//" local="2825443620671320542" remote="3472963200" /><file name="right_arrow.png" server="linnard.com//" local="2825452416746495364" remote="3469420800" /><file name="speakers.jpg" server="linnard.com//" local="689173891763007131" remote="3472963200" /><file name="speakers_470.jpg" server="linnard.com//" local="687245348364285914" remote="3469420800" /><file name="splotch_13_470.jpg" server="linnard.com//" local="685422358085430665" remote="3469420800" /><file name="splotch_313.jpg" server="linnard.com//" local="685431154182072536" remote="3473049600" /><file name="splotch_315.jpg" server="linnard.com//" local="689776424135042076" remote="3473049600" /><file name="splotch_316.jpg" server="linnard.com//" local="689785220228066663" remote="3473049600" /><file name="splotch_317.jpg" server="linnard.com//" local="689103523018843922" remote="3473049600" /><file name="splotch_318.jpg" server="linnard.com//" local="689112319111866280" remote="3473049600" /><file name="splotch_319.jpg" server="linnard.com//" local="685629066257748836" remote="3469420800" /><file name="splotch_320.jpg" server="linnard.com//" local="685637862350771044" remote="3469420800" /><file name="sub_bubbles.jpg" server="linnard.com//" local="685646658461113966" remote="3473049600" /><file name="sub_set.jpg" server="linnard.com//" local="689365206786252309" remote="3473049600" /><file name="sub_set.psd" server="linnard.com//" local="689374002870322632" remote="3469420800" /><file name="sub_set2.jpg" server="linnard.com//" local="689382798961886420" remote="3469420800" /><file name="sub_set2.psd" server="linnard.com//" local="687227756172903880" remote="3469420800" /><file name="sub_set3.jpg" server="linnard.com//" local="2825470008950398456" remote="-1" /><file name="teddy02.gif" server="linnard.com//" local="2819136821953527160" remote="3469420800" /><file name="teddy1.jpg" server="linnard.com//" local="2120458755170216639" remote="3469420800" /><file name="teddy1.png" server="linnard.com//" local="2124808423152516592" remote="3469420800" /><file name="teddy10.gif" server="linnard.com//" local="2124817219245538680" remote="3469420800" /><file name="teddy13.gif" server="linnard.com//" local="2124826015338560888" remote="3469420800" /><file name="teddy2.jpg" server="linnard.com//" local="2124834811448765412" remote="3469420800" /><file name="teddy3.jpg" server="linnard.com//" local="2124843607541848350" remote="3469420800" /><file name="transistor2.jpg" server="linnard.com//" local="2124852403638497141" remote="3472963200" /><file name="twill.jpg" server="linnard.com//" local="2124861199714182761" remote="3469420800" /><file name="twill2.jpg" server="linnard.com//" local="2124869995807230708" remote="3469420800" /><file name="yellow1.jpg" server="linnard.com//" local="2124887588010597673" remote="3473049600" /><file name="yellow1_470.jpg" server="linnard.com//" local="2124896384100005338" remote="3469420800" /><file name="zero_stock.jpg" server="linnard.com//" local="2124905180179566620" remote="3469420800" /><file name="zero_stock2.jpg" server="linnard.com//" local="2124913976272588888" remote="3469420800" /></dwsync>